{
  "type_description_msg": {
    "type_description": {
      "type_name": "autonomy_interfaces/action/NavigateToPose",
      "fields": [
        {
          "name": "goal",
          "type": {
            "type_id": 1,
            "capacity": 0,
            "string_capacity": 0,
            "nested_type_name": "autonomy_interfaces/action/NavigateToPose_Goal"
          },
          "default_value": ""
        },
        {
          "name": "result",
          "type": {
            "type_id": 1,
            "capacity": 0,
            "string_capacity": 0,
            "nested_type_name": "autonomy_interfaces/action/NavigateToPose_Result"
          },
          "default_value": ""
        },
        {
          "name": "feedback",
          "type": {
            "type_id": 1,
            "capacity": 0,
            "string_capacity": 0,
            "nested_type_name": "autonomy_interfaces/action/NavigateToPose_Feedback"
          },
          "default_value": ""
        },
        {
          "name": "send_goal_service",
          "type": {
            "type_id": 1,
            "capacity": 0,
            "string_capacity": 0,
            "nested_type_name": "autonomy_interfaces/action/NavigateToPose_SendGoal"
          },
          "default_value": ""
        },
        {
          "name": "get_result_service",
          "type": {
            "type_id": 1,
            "capacity": 0,
            "string_capacity": 0,
            "nested_type_name": "autonomy_interfaces/action/NavigateToPose_GetResult"
          },
          "default_value": ""
        },
        {
          "name": "feedback_message",
          "type": {
            "type_id": 1,
            "capacity": 0,
            "string_capacity": 0,
            "nested_type_name": "autonomy_interfaces/action/NavigateToPose_FeedbackMessage"
          },
          "default_value": ""
        }
      ]
    },
    "referenced_type_descriptions": [
      {
        "type_name": "autonomy_interfaces/action/NavigateToPose_Feedback",
        "fields": [
          {
            "name": "success",
            "type": {
              "type_id": 15,
              "capacity": 0,
              "string_capacity": 0,
              "nested_type_name": ""
            },
            "default_value": ""
          },
          {
            "name": "message",
            "type": {
              "type_id": 17,
              "capacity": 0,
              "string_capacity": 0,
              "nested_type_name": ""
            },
            "default_value": ""
          },
          {
            "name": "final_pose",
            "type": {
              "type_id": 1,
              "capacity": 0,
              "string_capacity": 0,
              "nested_type_name": "geometry_msgs/msg/PoseStamped"
            },
            "default_value": ""
          },
          {
            "name": "total_distance_traveled",
            "type": {
              "type_id": 10,
              "capacity": 0,
              "string_capacity": 0,
              "nested_type_name": ""
            },
            "default_value": ""
          },
          {
            "name": "total_time",
            "type": {
              "type_id": 10,
              "capacity": 0,
              "string_capacity": 0,
              "nested_type_name": ""
            },
            "default_value": ""
          }
        ]
      },
      {
        "type_name": "autonomy_interfaces/action/NavigateToPose_FeedbackMessage",
        "fields": [
          {
            "name": "goal_id",
            "type": {
              "type_id": 1,
              "capacity": 0,
              "string_capacity": 0,
              "nested_type_name": "unique_identifier_msgs/msg/UUID"
            },
            "default_value": ""
          },
          {
            "name": "feedback",
            "type": {
              "type_id": 1,
              "capacity": 0,
              "string_capacity": 0,
              "nested_type_name": "autonomy_interfaces/action/NavigateToPose_Feedback"
            },
            "default_value": ""
          }
        ]
      },
      {
        "type_name": "autonomy_interfaces/action/NavigateToPose_GetResult",
        "fields": [
          {
            "name": "request_message",
            "type": {
              "type_id": 1,
              "capacity": 0,
              "string_capacity": 0,
              "nested_type_name": "autonomy_interfaces/action/NavigateToPose_GetResult_Request"
            },
            "default_value": ""
          },
          {
            "name": "response_message",
            "type": {
              "type_id": 1,
              "capacity": 0,
              "string_capacity": 0,
              "nested_type_name": "autonomy_interfaces/action/NavigateToPose_GetResult_Response"
            },
            "default_value": ""
          },
          {
            "name": "event_message",
            "type": {
              "type_id": 1,
              "capacity": 0,
              "string_capacity": 0,
              "nested_type_name": "autonomy_interfaces/action/NavigateToPose_GetResult_Event"
            },
            "default_value": ""
          }
        ]
      },
      {
        "type_name": "autonomy_interfaces/action/NavigateToPose_GetResult_Event",
        "fields": [
          {
            "name": "info",
            "type": {
              "type_id": 1,
              "capacity": 0,
              "string_capacity": 0,
              "nested_type_name": "service_msgs/msg/ServiceEventInfo"
            },
            "default_value": ""
          },
          {
            "name": "request",
            "type": {
              "type_id": 97,
              "capacity": 1,
              "string_capacity": 0,
              "nested_type_name": "autonomy_interfaces/action/NavigateToPose_GetResult_Request"
            },
            "default_value": ""
          },
          {
            "name": "response",
            "type": {
              "type_id": 97,
              "capacity": 1,
              "string_capacity": 0,
              "nested_type_name": "autonomy_interfaces/action/NavigateToPose_GetResult_Response"
            },
            "default_value": ""
          }
        ]
      },
      {
        "type_name": "autonomy_interfaces/action/NavigateToPose_GetResult_Request",
        "fields": [
          {
            "name": "goal_id",
            "type": {
              "type_id": 1,
              "capacity": 0,
              "string_capacity": 0,
              "nested_type_name": "unique_identifier_msgs/msg/UUID"
            },
            "default_value": ""
          }
        ]
      },
      {
        "type_name": "autonomy_interfaces/action/NavigateToPose_GetResult_Response",
        "fields": [
          {
            "name": "status",
            "type": {
              "type_id": 2,
              "capacity": 0,
              "string_capacity": 0,
              "nested_type_name": ""
            },
            "default_value": ""
          },
          {
            "name": "result",
            "type": {
              "type_id": 1,
              "capacity": 0,
              "string_capacity": 0,
              "nested_type_name": "autonomy_interfaces/action/NavigateToPose_Result"
            },
            "default_value": ""
          }
        ]
      },
      {
        "type_name": "autonomy_interfaces/action/NavigateToPose_Goal",
        "fields": [
          {
            "name": "target_pose",
            "type": {
              "type_id": 1,
              "capacity": 0,
              "string_capacity": 0,
              "nested_type_name": "geometry_msgs/msg/PoseStamped"
            },
            "default_value": ""
          },
          {
            "name": "tolerance",
            "type": {
              "type_id": 10,
              "capacity": 0,
              "string_capacity": 0,
              "nested_type_name": ""
            },
            "default_value": ""
          },
          {
            "name": "timeout",
            "type": {
              "type_id": 10,
              "capacity": 0,
              "string_capacity": 0,
              "nested_type_name": ""
            },
            "default_value": ""
          }
        ]
      },
      {
        "type_name": "autonomy_interfaces/action/NavigateToPose_Result",
        "fields": [
          {
            "name": "distance_to_goal",
            "type": {
              "type_id": 10,
              "capacity": 0,
              "string_capacity": 0,
              "nested_type_name": ""
            },
            "default_value": ""
          },
          {
            "name": "estimated_time_remaining",
            "type": {
              "type_id": 10,
              "capacity": 0,
              "string_capacity": 0,
              "nested_type_name": ""
            },
            "default_value": ""
          },
          {
            "name": "navigation_state",
            "type": {
              "type_id": 17,
              "capacity": 0,
              "string_capacity": 0,
              "nested_type_name": ""
            },
            "default_value": ""
          },
          {
            "name": "current_pose",
            "type": {
              "type_id": 1,
              "capacity": 0,
              "string_capacity": 0,
              "nested_type_name": "geometry_msgs/msg/PoseStamped"
            },
            "default_value": ""
          }
        ]
      },
      {
        "type_name": "autonomy_interfaces/action/NavigateToPose_SendGoal",
        "fields": [
          {
            "name": "request_message",
            "type": {
              "type_id": 1,
              "capacity": 0,
              "string_capacity": 0,
              "nested_type_name": "autonomy_interfaces/action/NavigateToPose_SendGoal_Request"
            },
            "default_value": ""
          },
          {
            "name": "response_message",
            "type": {
              "type_id": 1,
              "capacity": 0,
              "string_capacity": 0,
              "nested_type_name": "autonomy_interfaces/action/NavigateToPose_SendGoal_Response"
            },
            "default_value": ""
          },
          {
            "name": "event_message",
            "type": {
              "type_id": 1,
              "capacity": 0,
              "string_capacity": 0,
              "nested_type_name": "autonomy_interfaces/action/NavigateToPose_SendGoal_Event"
            },
            "default_value": ""
          }
        ]
      },
      {
        "type_name": "autonomy_interfaces/action/NavigateToPose_SendGoal_Event",
        "fields": [
          {
            "name": "info",
            "type": {
              "type_id": 1,
              "capacity": 0,
              "string_capacity": 0,
              "nested_type_name": "service_msgs/msg/ServiceEventInfo"
            },
            "default_value": ""
          },
          {
            "name": "request",
            "type": {
              "type_id": 97,
              "capacity": 1,
              "string_capacity": 0,
              "nested_type_name": "autonomy_interfaces/action/NavigateToPose_SendGoal_Request"
            },
            "default_value": ""
          },
          {
            "name": "response",
            "type": {
              "type_id": 97,
              "capacity": 1,
              "string_capacity": 0,
              "nested_type_name": "autonomy_interfaces/action/NavigateToPose_SendGoal_Response"
            },
            "default_value": ""
          }
        ]
      },
      {
        "type_name": "autonomy_interfaces/action/NavigateToPose_SendGoal_Request",
        "fields": [
          {
            "name": "goal_id",
            "type": {
              "type_id": 1,
              "capacity": 0,
              "string_capacity": 0,
              "nested_type_name": "unique_identifier_msgs/msg/UUID"
            },
            "default_value": ""
          },
          {
            "name": "goal",
            "type": {
              "type_id": 1,
              "capacity": 0,
              "string_capacity": 0,
              "nested_type_name": "autonomy_interfaces/action/NavigateToPose_Goal"
            },
            "default_value": ""
          }
        ]
      },
      {
        "type_name": "autonomy_interfaces/action/NavigateToPose_SendGoal_Response",
        "fields": [
          {
            "name": "accepted",
            "type": {
              "type_id": 15,
              "capacity": 0,
              "string_capacity": 0,
              "nested_type_name": ""
            },
            "default_value": ""
          },
          {
            "name": "stamp",
            "type": {
              "type_id": 1,
              "capacity": 0,
              "string_capacity": 0,
              "nested_type_name": "builtin_interfaces/msg/Time"
            },
            "default_value": ""
          }
        ]
      },
      {
        "type_name": "builtin_interfaces/msg/Time",
        "fields": [
          {
            "name": "sec",
            "type": {
              "type_id": 6,
              "capacity": 0,
              "string_capacity": 0,
              "nested_type_name": ""
            },
            "default_value": ""
          },
          {
            "name": "nanosec",
            "type": {
              "type_id": 7,
              "capacity": 0,
              "string_capacity": 0,
              "nested_type_name": ""
            },
            "default_value": ""
          }
        ]
      },
      {
        "type_name": "geometry_msgs/msg/Point",
        "fields": [
          {
            "name": "x",
            "type": {
              "type_id": 11,
              "capacity": 0,
              "string_capacity": 0,
              "nested_type_name": ""
            },
            "default_value": ""
          },
          {
            "name": "y",
            "type": {
              "type_id": 11,
              "capacity": 0,
              "string_capacity": 0,
              "nested_type_name": ""
            },
            "default_value": ""
          },
          {
            "name": "z",
            "type": {
              "type_id": 11,
              "capacity": 0,
              "string_capacity": 0,
              "nested_type_name": ""
            },
            "default_value": ""
          }
        ]
      },
      {
        "type_name": "geometry_msgs/msg/Pose",
        "fields": [
          {
            "name": "position",
            "type": {
              "type_id": 1,
              "capacity": 0,
              "string_capacity": 0,
              "nested_type_name": "geometry_msgs/msg/Point"
            },
            "default_value": ""
          },
          {
            "name": "orientation",
            "type": {
              "type_id": 1,
              "capacity": 0,
              "string_capacity": 0,
              "nested_type_name": "geometry_msgs/msg/Quaternion"
            },
            "default_value": ""
          }
        ]
      },
      {
        "type_name": "geometry_msgs/msg/PoseStamped",
        "fields": [
          {
            "name": "header",
            "type": {
              "type_id": 1,
              "capacity": 0,
              "string_capacity": 0,
              "nested_type_name": "std_msgs/msg/Header"
            },
            "default_value": ""
          },
          {
            "name": "pose",
            "type": {
              "type_id": 1,
              "capacity": 0,
              "string_capacity": 0,
              "nested_type_name": "geometry_msgs/msg/Pose"
            },
            "default_value": ""
          }
        ]
      },
      {
        "type_name": "geometry_msgs/msg/Quaternion",
        "fields": [
          {
            "name": "x",
            "type": {
              "type_id": 11,
              "capacity": 0,
              "string_capacity": 0,
              "nested_type_name": ""
            },
            "default_value": "0.0"
          },
          {
            "name": "y",
            "type": {
              "type_id": 11,
              "capacity": 0,
              "string_capacity": 0,
              "nested_type_name": ""
            },
            "default_value": "0.0"
          },
          {
            "name": "z",
            "type": {
              "type_id": 11,
              "capacity": 0,
              "string_capacity": 0,
              "nested_type_name": ""
            },
            "default_value": "0.0"
          },
          {
            "name": "w",
            "type": {
              "type_id": 11,
              "capacity": 0,
              "string_capacity": 0,
              "nested_type_name": ""
            },
            "default_value": "1.0"
          }
        ]
      },
      {
        "type_name": "service_msgs/msg/ServiceEventInfo",
        "fields": [
          {
            "name": "event_type",
            "type": {
              "type_id": 3,
              "capacity": 0,
              "string_capacity": 0,
              "nested_type_name": ""
            },
            "default_value": ""
          },
          {
            "name": "stamp",
            "type": {
              "type_id": 1,
              "capacity": 0,
              "string_capacity": 0,
              "nested_type_name": "builtin_interfaces/msg/Time"
            },
            "default_value": ""
          },
          {
            "name": "client_gid",
            "type": {
              "type_id": 51,
              "capacity": 16,
              "string_capacity": 0,
              "nested_type_name": ""
            },
            "default_value": ""
          },
          {
            "name": "sequence_number",
            "type": {
              "type_id": 8,
              "capacity": 0,
              "string_capacity": 0,
              "nested_type_name": ""
            },
            "default_value": ""
          }
        ]
      },
      {
        "type_name": "std_msgs/msg/Header",
        "fields": [
          {
            "name": "stamp",
            "type": {
              "type_id": 1,
              "capacity": 0,
              "string_capacity": 0,
              "nested_type_name": "builtin_interfaces/msg/Time"
            },
            "default_value": ""
          },
          {
            "name": "frame_id",
            "type": {
              "type_id": 17,
              "capacity": 0,
              "string_capacity": 0,
              "nested_type_name": ""
            },
            "default_value": ""
          }
        ]
      },
      {
        "type_name": "unique_identifier_msgs/msg/UUID",
        "fields": [
          {
            "name": "uuid",
            "type": {
              "type_id": 51,
              "capacity": 16,
              "string_capacity": 0,
              "nested_type_name": ""
            },
            "default_value": ""
          }
        ]
      }
    ]
  },
  "type_hashes": [
    {
      "type_name": "autonomy_interfaces/action/NavigateToPose",
      "hash_string": "RIHS01_866d36f34c24e519b9f3f8c9977cab883f20e148da9c75728051dc3f64a6db56"
    },
    {
      "type_name": "autonomy_interfaces/action/NavigateToPose_Feedback",
      "hash_string": "RIHS01_6984748de5c43d8c8630f06a340917aae902b8b3bde4bf12823e5c4f48330edf"
    },
    {
      "type_name": "autonomy_interfaces/action/NavigateToPose_FeedbackMessage",
      "hash_string": "RIHS01_e7c399001ecb672a7f145c5b8185effc62fd3721336929d067641d0c0c044275"
    },
    {
      "type_name": "autonomy_interfaces/action/NavigateToPose_GetResult",
      "hash_string": "RIHS01_ec6b10032923cd514883597699f5f45cfcdba75b3421b4cedce9e046066a608e"
    },
    {
      "type_name": "autonomy_interfaces/action/NavigateToPose_GetResult_Event",
      "hash_string": "RIHS01_1e04a7bfda97e0fc6388044610738e408d13237af8970c8fd4aa3e04d86fe48f"
    },
    {
      "type_name": "autonomy_interfaces/action/NavigateToPose_GetResult_Request",
      "hash_string": "RIHS01_53e11a196b5fe99f9dd7039918a253f0f73f44455889fe3fe97d8be2ed1f45c0"
    },
    {
      "type_name": "autonomy_interfaces/action/NavigateToPose_GetResult_Response",
      "hash_string": "RIHS01_598cf72ab2ee001d59fc8b1f9c972b718840b6333395801c9491791636855a0e"
    },
    {
      "type_name": "autonomy_interfaces/action/NavigateToPose_Goal",
      "hash_string": "RIHS01_eb1de667569ddc166565821443269ee50bd42933b573961de00bc65e29884522"
    },
    {
      "type_name": "autonomy_interfaces/action/NavigateToPose_Result",
      "hash_string": "RIHS01_76fd6a63921fde405cc6de8daa595c99da540ba892d0ec393473f1a02447c13f"
    },
    {
      "type_name": "autonomy_interfaces/action/NavigateToPose_SendGoal",
      "hash_string": "RIHS01_fa4c7192fcb1e74f86864825ce729297802bce0a0da6880329e2995367bb9881"
    },
    {
      "type_name": "autonomy_interfaces/action/NavigateToPose_SendGoal_Event",
      "hash_string": "RIHS01_269d2c1294bb30592d27e4df6a93785b971d1d2e60637aa27a2ec94f7101eaae"
    },
    {
      "type_name": "autonomy_interfaces/action/NavigateToPose_SendGoal_Request",
      "hash_string": "RIHS01_9842ba6496788dd5defce70c0e93aac6a8a487b42a48635e8f37859cefb076ec"
    },
    {
      "type_name": "autonomy_interfaces/action/NavigateToPose_SendGoal_Response",
      "hash_string": "RIHS01_ba80f2c84e3b0cb067ae78084ea572fde0349a02611edd3431ff0ef09ca3d582"
    },
    {
      "type_name": "builtin_interfaces/msg/Time",
      "hash_string": "RIHS01_b106235e25a4c5ed35098aa0a61a3ee9c9b18d197f398b0e4206cea9acf9c197"
    },
    {
      "type_name": "geometry_msgs/msg/Point",
      "hash_string": "RIHS01_6963084842a9b04494d6b2941d11444708d892da2f4b09843b9c43f42a7f6881"
    },
    {
      "type_name": "geometry_msgs/msg/Pose",
      "hash_string": "RIHS01_d501954e9476cea2996984e812054b68026ae0bfae789d9a10b23daf35cc90fa"
    },
    {
      "type_name": "geometry_msgs/msg/PoseStamped",
      "hash_string": "RIHS01_10f3786d7d40fd2b54367835614bff85d4ad3b5dab62bf8bca0cc232d73b4cd8"
    },
    {
      "type_name": "geometry_msgs/msg/Quaternion",
      "hash_string": "RIHS01_8a765f66778c8ff7c8ab94afcc590a2ed5325a1d9a076ffff38fbce36f458684"
    },
    {
      "type_name": "service_msgs/msg/ServiceEventInfo",
      "hash_string": "RIHS01_41bcbbe07a75c9b52bc96bfd5c24d7f0fc0a08c0cb7921b3373c5732345a6f45"
    },
    {
      "type_name": "std_msgs/msg/Header",
      "hash_string": "RIHS01_f49fb3ae2cf070f793645ff749683ac6b06203e41c891e17701b1cb597ce6a01"
    },
    {
      "type_name": "unique_identifier_msgs/msg/UUID",
      "hash_string": "RIHS01_1b8e8aca958cbea28fe6ef60bf6c19b683c97a9ef60bb34752067d0f2f7ab437"
    }
  ]
}