{
  "type_description_msg": {
    "type_description": {
      "type_name": "autonomy_interfaces/action/PerformTyping",
      "fields": [
        {
          "name": "goal",
          "type": {
            "type_id": 1,
            "capacity": 0,
            "string_capacity": 0,
            "nested_type_name": "autonomy_interfaces/action/PerformTyping_Goal"
          },
          "default_value": ""
        },
        {
          "name": "result",
          "type": {
            "type_id": 1,
            "capacity": 0,
            "string_capacity": 0,
            "nested_type_name": "autonomy_interfaces/action/PerformTyping_Result"
          },
          "default_value": ""
        },
        {
          "name": "feedback",
          "type": {
            "type_id": 1,
            "capacity": 0,
            "string_capacity": 0,
            "nested_type_name": "autonomy_interfaces/action/PerformTyping_Feedback"
          },
          "default_value": ""
        },
        {
          "name": "send_goal_service",
          "type": {
            "type_id": 1,
            "capacity": 0,
            "string_capacity": 0,
            "nested_type_name": "autonomy_interfaces/action/PerformTyping_SendGoal"
          },
          "default_value": ""
        },
        {
          "name": "get_result_service",
          "type": {
            "type_id": 1,
            "capacity": 0,
            "string_capacity": 0,
            "nested_type_name": "autonomy_interfaces/action/PerformTyping_GetResult"
          },
          "default_value": ""
        },
        {
          "name": "feedback_message",
          "type": {
            "type_id": 1,
            "capacity": 0,
            "string_capacity": 0,
            "nested_type_name": "autonomy_interfaces/action/PerformTyping_FeedbackMessage"
          },
          "default_value": ""
        }
      ]
    },
    "referenced_type_descriptions": [
      {
        "type_name": "autonomy_interfaces/action/PerformTyping_Feedback",
        "fields": [
          {
            "name": "success",
            "type": {
              "type_id": 15,
              "capacity": 0,
              "string_capacity": 0,
              "nested_type_name": ""
            },
            "default_value": ""
          },
          {
            "name": "message",
            "type": {
              "type_id": 17,
              "capacity": 0,
              "string_capacity": 0,
              "nested_type_name": ""
            },
            "default_value": ""
          },
          {
            "name": "text_typed",
            "type": {
              "type_id": 17,
              "capacity": 0,
              "string_capacity": 0,
              "nested_type_name": ""
            },
            "default_value": ""
          },
          {
            "name": "characters_attempted",
            "type": {
              "type_id": 6,
              "capacity": 0,
              "string_capacity": 0,
              "nested_type_name": ""
            },
            "default_value": ""
          },
          {
            "name": "characters_successful",
            "type": {
              "type_id": 6,
              "capacity": 0,
              "string_capacity": 0,
              "nested_type_name": ""
            },
            "default_value": ""
          },
          {
            "name": "accuracy",
            "type": {
              "type_id": 10,
              "capacity": 0,
              "string_capacity": 0,
              "nested_type_name": ""
            },
            "default_value": ""
          },
          {
            "name": "total_time",
            "type": {
              "type_id": 10,
              "capacity": 0,
              "string_capacity": 0,
              "nested_type_name": ""
            },
            "default_value": ""
          }
        ]
      },
      {
        "type_name": "autonomy_interfaces/action/PerformTyping_FeedbackMessage",
        "fields": [
          {
            "name": "goal_id",
            "type": {
              "type_id": 1,
              "capacity": 0,
              "string_capacity": 0,
              "nested_type_name": "unique_identifier_msgs/msg/UUID"
            },
            "default_value": ""
          },
          {
            "name": "feedback",
            "type": {
              "type_id": 1,
              "capacity": 0,
              "string_capacity": 0,
              "nested_type_name": "autonomy_interfaces/action/PerformTyping_Feedback"
            },
            "default_value": ""
          }
        ]
      },
      {
        "type_name": "autonomy_interfaces/action/PerformTyping_GetResult",
        "fields": [
          {
            "name": "request_message",
            "type": {
              "type_id": 1,
              "capacity": 0,
              "string_capacity": 0,
              "nested_type_name": "autonomy_interfaces/action/PerformTyping_GetResult_Request"
            },
            "default_value": ""
          },
          {
            "name": "response_message",
            "type": {
              "type_id": 1,
              "capacity": 0,
              "string_capacity": 0,
              "nested_type_name": "autonomy_interfaces/action/PerformTyping_GetResult_Response"
            },
            "default_value": ""
          },
          {
            "name": "event_message",
            "type": {
              "type_id": 1,
              "capacity": 0,
              "string_capacity": 0,
              "nested_type_name": "autonomy_interfaces/action/PerformTyping_GetResult_Event"
            },
            "default_value": ""
          }
        ]
      },
      {
        "type_name": "autonomy_interfaces/action/PerformTyping_GetResult_Event",
        "fields": [
          {
            "name": "info",
            "type": {
              "type_id": 1,
              "capacity": 0,
              "string_capacity": 0,
              "nested_type_name": "service_msgs/msg/ServiceEventInfo"
            },
            "default_value": ""
          },
          {
            "name": "request",
            "type": {
              "type_id": 97,
              "capacity": 1,
              "string_capacity": 0,
              "nested_type_name": "autonomy_interfaces/action/PerformTyping_GetResult_Request"
            },
            "default_value": ""
          },
          {
            "name": "response",
            "type": {
              "type_id": 97,
              "capacity": 1,
              "string_capacity": 0,
              "nested_type_name": "autonomy_interfaces/action/PerformTyping_GetResult_Response"
            },
            "default_value": ""
          }
        ]
      },
      {
        "type_name": "autonomy_interfaces/action/PerformTyping_GetResult_Request",
        "fields": [
          {
            "name": "goal_id",
            "type": {
              "type_id": 1,
              "capacity": 0,
              "string_capacity": 0,
              "nested_type_name": "unique_identifier_msgs/msg/UUID"
            },
            "default_value": ""
          }
        ]
      },
      {
        "type_name": "autonomy_interfaces/action/PerformTyping_GetResult_Response",
        "fields": [
          {
            "name": "status",
            "type": {
              "type_id": 2,
              "capacity": 0,
              "string_capacity": 0,
              "nested_type_name": ""
            },
            "default_value": ""
          },
          {
            "name": "result",
            "type": {
              "type_id": 1,
              "capacity": 0,
              "string_capacity": 0,
              "nested_type_name": "autonomy_interfaces/action/PerformTyping_Result"
            },
            "default_value": ""
          }
        ]
      },
      {
        "type_name": "autonomy_interfaces/action/PerformTyping_Goal",
        "fields": [
          {
            "name": "typing_goal",
            "type": {
              "type_id": 1,
              "capacity": 0,
              "string_capacity": 0,
              "nested_type_name": "autonomy_interfaces/msg/TypingGoal"
            },
            "default_value": ""
          }
        ]
      },
      {
        "type_name": "autonomy_interfaces/action/PerformTyping_Result",
        "fields": [
          {
            "name": "progress",
            "type": {
              "type_id": 10,
              "capacity": 0,
              "string_capacity": 0,
              "nested_type_name": ""
            },
            "default_value": ""
          },
          {
            "name": "current_character",
            "type": {
              "type_id": 17,
              "capacity": 0,
              "string_capacity": 0,
              "nested_type_name": ""
            },
            "default_value": ""
          },
          {
            "name": "characters_completed",
            "type": {
              "type_id": 6,
              "capacity": 0,
              "string_capacity": 0,
              "nested_type_name": ""
            },
            "default_value": ""
          },
          {
            "name": "current_hand_pose",
            "type": {
              "type_id": 1,
              "capacity": 0,
              "string_capacity": 0,
              "nested_type_name": "geometry_msgs/msg/PoseStamped"
            },
            "default_value": ""
          }
        ]
      },
      {
        "type_name": "autonomy_interfaces/action/PerformTyping_SendGoal",
        "fields": [
          {
            "name": "request_message",
            "type": {
              "type_id": 1,
              "capacity": 0,
              "string_capacity": 0,
              "nested_type_name": "autonomy_interfaces/action/PerformTyping_SendGoal_Request"
            },
            "default_value": ""
          },
          {
            "name": "response_message",
            "type": {
              "type_id": 1,
              "capacity": 0,
              "string_capacity": 0,
              "nested_type_name": "autonomy_interfaces/action/PerformTyping_SendGoal_Response"
            },
            "default_value": ""
          },
          {
            "name": "event_message",
            "type": {
              "type_id": 1,
              "capacity": 0,
              "string_capacity": 0,
              "nested_type_name": "autonomy_interfaces/action/PerformTyping_SendGoal_Event"
            },
            "default_value": ""
          }
        ]
      },
      {
        "type_name": "autonomy_interfaces/action/PerformTyping_SendGoal_Event",
        "fields": [
          {
            "name": "info",
            "type": {
              "type_id": 1,
              "capacity": 0,
              "string_capacity": 0,
              "nested_type_name": "service_msgs/msg/ServiceEventInfo"
            },
            "default_value": ""
          },
          {
            "name": "request",
            "type": {
              "type_id": 97,
              "capacity": 1,
              "string_capacity": 0,
              "nested_type_name": "autonomy_interfaces/action/PerformTyping_SendGoal_Request"
            },
            "default_value": ""
          },
          {
            "name": "response",
            "type": {
              "type_id": 97,
              "capacity": 1,
              "string_capacity": 0,
              "nested_type_name": "autonomy_interfaces/action/PerformTyping_SendGoal_Response"
            },
            "default_value": ""
          }
        ]
      },
      {
        "type_name": "autonomy_interfaces/action/PerformTyping_SendGoal_Request",
        "fields": [
          {
            "name": "goal_id",
            "type": {
              "type_id": 1,
              "capacity": 0,
              "string_capacity": 0,
              "nested_type_name": "unique_identifier_msgs/msg/UUID"
            },
            "default_value": ""
          },
          {
            "name": "goal",
            "type": {
              "type_id": 1,
              "capacity": 0,
              "string_capacity": 0,
              "nested_type_name": "autonomy_interfaces/action/PerformTyping_Goal"
            },
            "default_value": ""
          }
        ]
      },
      {
        "type_name": "autonomy_interfaces/action/PerformTyping_SendGoal_Response",
        "fields": [
          {
            "name": "accepted",
            "type": {
              "type_id": 15,
              "capacity": 0,
              "string_capacity": 0,
              "nested_type_name": ""
            },
            "default_value": ""
          },
          {
            "name": "stamp",
            "type": {
              "type_id": 1,
              "capacity": 0,
              "string_capacity": 0,
              "nested_type_name": "builtin_interfaces/msg/Time"
            },
            "default_value": ""
          }
        ]
      },
      {
        "type_name": "autonomy_interfaces/msg/TypingGoal",
        "fields": [
          {
            "name": "header",
            "type": {
              "type_id": 1,
              "capacity": 0,
              "string_capacity": 0,
              "nested_type_name": "std_msgs/msg/Header"
            },
            "default_value": ""
          },
          {
            "name": "target_text",
            "type": {
              "type_id": 17,
              "capacity": 0,
              "string_capacity": 0,
              "nested_type_name": ""
            },
            "default_value": ""
          },
          {
            "name": "keyboard_pose",
            "type": {
              "type_id": 1,
              "capacity": 0,
              "string_capacity": 0,
              "nested_type_name": "geometry_msgs/msg/PoseStamped"
            },
            "default_value": ""
          },
          {
            "name": "accuracy_requirement",
            "type": {
              "type_id": 10,
              "capacity": 0,
              "string_capacity": 0,
              "nested_type_name": ""
            },
            "default_value": ""
          },
          {
            "name": "speed_requirement",
            "type": {
              "type_id": 10,
              "capacity": 0,
              "string_capacity": 0,
              "nested_type_name": ""
            },
            "default_value": ""
          },
          {
            "name": "timeout",
            "type": {
              "type_id": 10,
              "capacity": 0,
              "string_capacity": 0,
              "nested_type_name": ""
            },
            "default_value": ""
          },
          {
            "name": "keyboard_layout",
            "type": {
              "type_id": 17,
              "capacity": 0,
              "string_capacity": 0,
              "nested_type_name": ""
            },
            "default_value": ""
          },
          {
            "name": "key_spacing_m",
            "type": {
              "type_id": 10,
              "capacity": 0,
              "string_capacity": 0,
              "nested_type_name": ""
            },
            "default_value": ""
          },
          {
            "name": "key_dimensions",
            "type": {
              "type_id": 1,
              "capacity": 0,
              "string_capacity": 0,
              "nested_type_name": "geometry_msgs/msg/Vector3"
            },
            "default_value": ""
          },
          {
            "name": "standoff_distance",
            "type": {
              "type_id": 10,
              "capacity": 0,
              "string_capacity": 0,
              "nested_type_name": ""
            },
            "default_value": ""
          },
          {
            "name": "contact_force",
            "type": {
              "type_id": 10,
              "capacity": 0,
              "string_capacity": 0,
              "nested_type_name": ""
            },
            "default_value": ""
          }
        ]
      },
      {
        "type_name": "builtin_interfaces/msg/Time",
        "fields": [
          {
            "name": "sec",
            "type": {
              "type_id": 6,
              "capacity": 0,
              "string_capacity": 0,
              "nested_type_name": ""
            },
            "default_value": ""
          },
          {
            "name": "nanosec",
            "type": {
              "type_id": 7,
              "capacity": 0,
              "string_capacity": 0,
              "nested_type_name": ""
            },
            "default_value": ""
          }
        ]
      },
      {
        "type_name": "geometry_msgs/msg/Point",
        "fields": [
          {
            "name": "x",
            "type": {
              "type_id": 11,
              "capacity": 0,
              "string_capacity": 0,
              "nested_type_name": ""
            },
            "default_value": ""
          },
          {
            "name": "y",
            "type": {
              "type_id": 11,
              "capacity": 0,
              "string_capacity": 0,
              "nested_type_name": ""
            },
            "default_value": ""
          },
          {
            "name": "z",
            "type": {
              "type_id": 11,
              "capacity": 0,
              "string_capacity": 0,
              "nested_type_name": ""
            },
            "default_value": ""
          }
        ]
      },
      {
        "type_name": "geometry_msgs/msg/Pose",
        "fields": [
          {
            "name": "position",
            "type": {
              "type_id": 1,
              "capacity": 0,
              "string_capacity": 0,
              "nested_type_name": "geometry_msgs/msg/Point"
            },
            "default_value": ""
          },
          {
            "name": "orientation",
            "type": {
              "type_id": 1,
              "capacity": 0,
              "string_capacity": 0,
              "nested_type_name": "geometry_msgs/msg/Quaternion"
            },
            "default_value": ""
          }
        ]
      },
      {
        "type_name": "geometry_msgs/msg/PoseStamped",
        "fields": [
          {
            "name": "header",
            "type": {
              "type_id": 1,
              "capacity": 0,
              "string_capacity": 0,
              "nested_type_name": "std_msgs/msg/Header"
            },
            "default_value": ""
          },
          {
            "name": "pose",
            "type": {
              "type_id": 1,
              "capacity": 0,
              "string_capacity": 0,
              "nested_type_name": "geometry_msgs/msg/Pose"
            },
            "default_value": ""
          }
        ]
      },
      {
        "type_name": "geometry_msgs/msg/Quaternion",
        "fields": [
          {
            "name": "x",
            "type": {
              "type_id": 11,
              "capacity": 0,
              "string_capacity": 0,
              "nested_type_name": ""
            },
            "default_value": "0.0"
          },
          {
            "name": "y",
            "type": {
              "type_id": 11,
              "capacity": 0,
              "string_capacity": 0,
              "nested_type_name": ""
            },
            "default_value": "0.0"
          },
          {
            "name": "z",
            "type": {
              "type_id": 11,
              "capacity": 0,
              "string_capacity": 0,
              "nested_type_name": ""
            },
            "default_value": "0.0"
          },
          {
            "name": "w",
            "type": {
              "type_id": 11,
              "capacity": 0,
              "string_capacity": 0,
              "nested_type_name": ""
            },
            "default_value": "1.0"
          }
        ]
      },
      {
        "type_name": "geometry_msgs/msg/Vector3",
        "fields": [
          {
            "name": "x",
            "type": {
              "type_id": 11,
              "capacity": 0,
              "string_capacity": 0,
              "nested_type_name": ""
            },
            "default_value": ""
          },
          {
            "name": "y",
            "type": {
              "type_id": 11,
              "capacity": 0,
              "string_capacity": 0,
              "nested_type_name": ""
            },
            "default_value": ""
          },
          {
            "name": "z",
            "type": {
              "type_id": 11,
              "capacity": 0,
              "string_capacity": 0,
              "nested_type_name": ""
            },
            "default_value": ""
          }
        ]
      },
      {
        "type_name": "service_msgs/msg/ServiceEventInfo",
        "fields": [
          {
            "name": "event_type",
            "type": {
              "type_id": 3,
              "capacity": 0,
              "string_capacity": 0,
              "nested_type_name": ""
            },
            "default_value": ""
          },
          {
            "name": "stamp",
            "type": {
              "type_id": 1,
              "capacity": 0,
              "string_capacity": 0,
              "nested_type_name": "builtin_interfaces/msg/Time"
            },
            "default_value": ""
          },
          {
            "name": "client_gid",
            "type": {
              "type_id": 51,
              "capacity": 16,
              "string_capacity": 0,
              "nested_type_name": ""
            },
            "default_value": ""
          },
          {
            "name": "sequence_number",
            "type": {
              "type_id": 8,
              "capacity": 0,
              "string_capacity": 0,
              "nested_type_name": ""
            },
            "default_value": ""
          }
        ]
      },
      {
        "type_name": "std_msgs/msg/Header",
        "fields": [
          {
            "name": "stamp",
            "type": {
              "type_id": 1,
              "capacity": 0,
              "string_capacity": 0,
              "nested_type_name": "builtin_interfaces/msg/Time"
            },
            "default_value": ""
          },
          {
            "name": "frame_id",
            "type": {
              "type_id": 17,
              "capacity": 0,
              "string_capacity": 0,
              "nested_type_name": ""
            },
            "default_value": ""
          }
        ]
      },
      {
        "type_name": "unique_identifier_msgs/msg/UUID",
        "fields": [
          {
            "name": "uuid",
            "type": {
              "type_id": 51,
              "capacity": 16,
              "string_capacity": 0,
              "nested_type_name": ""
            },
            "default_value": ""
          }
        ]
      }
    ]
  },
  "type_hashes": [
    {
      "type_name": "autonomy_interfaces/action/PerformTyping",
      "hash_string": "RIHS01_5ed9c8d7a6a7e209acf6ae618dd0dc08c08d344291b2b63d93364e561b58c719"
    },
    {
      "type_name": "autonomy_interfaces/action/PerformTyping_Feedback",
      "hash_string": "RIHS01_a0a0843a8b59a9ddfdd3ffd33e9a22e59e4bf7bd1cfe578178abac5cf7912910"
    },
    {
      "type_name": "autonomy_interfaces/action/PerformTyping_FeedbackMessage",
      "hash_string": "RIHS01_72d51799bc96d6c59e00440c544930d4a3fed88db4db683c5caf8275a1448b05"
    },
    {
      "type_name": "autonomy_interfaces/action/PerformTyping_GetResult",
      "hash_string": "RIHS01_666029f7680cd6a48cb55ff91f35657bd4c821b0d67e9c271d50020f9826331e"
    },
    {
      "type_name": "autonomy_interfaces/action/PerformTyping_GetResult_Event",
      "hash_string": "RIHS01_acae68e45d08e09c32aac5c89d8440fc0a04c78e9a2d50ddb354a9449d653714"
    },
    {
      "type_name": "autonomy_interfaces/action/PerformTyping_GetResult_Request",
      "hash_string": "RIHS01_5d2a52c2c4de4b9e43a03b30c9b4ca45e0ce197624389104cd730fbe4e1e8e68"
    },
    {
      "type_name": "autonomy_interfaces/action/PerformTyping_GetResult_Response",
      "hash_string": "RIHS01_5213d676e05abce5cbf6bc577771ba014f5d36259c819dd2effa8106d514c5f2"
    },
    {
      "type_name": "autonomy_interfaces/action/PerformTyping_Goal",
      "hash_string": "RIHS01_d2340b3611cdc316273471279af9686f8a80f1b8dc92df51176158eea153a986"
    },
    {
      "type_name": "autonomy_interfaces/action/PerformTyping_Result",
      "hash_string": "RIHS01_c73caede1ac274877bc6224026dec8d3cc5d441fbefed48bc46805ebe6200fc4"
    },
    {
      "type_name": "autonomy_interfaces/action/PerformTyping_SendGoal",
      "hash_string": "RIHS01_fcb231da773ca49f0b8a323eba9aa4b35e102a0acd7576181045a20db3704d75"
    },
    {
      "type_name": "autonomy_interfaces/action/PerformTyping_SendGoal_Event",
      "hash_string": "RIHS01_6518ea0e778517e477ad40e976331e2362a22f89ac2956a9af34895199868101"
    },
    {
      "type_name": "autonomy_interfaces/action/PerformTyping_SendGoal_Request",
      "hash_string": "RIHS01_7476cd24d7dc6f22f26221ba8d901da43b46d6e8599f2e0e23912861f8c74fc9"
    },
    {
      "type_name": "autonomy_interfaces/action/PerformTyping_SendGoal_Response",
      "hash_string": "RIHS01_ab184c505acc68620afd09f60757a9c16da814d09bb5ce1c022b32f0762fb5dc"
    },
    {
      "type_name": "autonomy_interfaces/msg/TypingGoal",
      "hash_string": "RIHS01_a7034b04432f03c1bb209f0ca16e7eba2be76245bd81cc241f35b1e2edf51e00"
    },
    {
      "type_name": "builtin_interfaces/msg/Time",
      "hash_string": "RIHS01_b106235e25a4c5ed35098aa0a61a3ee9c9b18d197f398b0e4206cea9acf9c197"
    },
    {
      "type_name": "geometry_msgs/msg/Point",
      "hash_string": "RIHS01_6963084842a9b04494d6b2941d11444708d892da2f4b09843b9c43f42a7f6881"
    },
    {
      "type_name": "geometry_msgs/msg/Pose",
      "hash_string": "RIHS01_d501954e9476cea2996984e812054b68026ae0bfae789d9a10b23daf35cc90fa"
    },
    {
      "type_name": "geometry_msgs/msg/PoseStamped",
      "hash_string": "RIHS01_10f3786d7d40fd2b54367835614bff85d4ad3b5dab62bf8bca0cc232d73b4cd8"
    },
    {
      "type_name": "geometry_msgs/msg/Quaternion",
      "hash_string": "RIHS01_8a765f66778c8ff7c8ab94afcc590a2ed5325a1d9a076ffff38fbce36f458684"
    },
    {
      "type_name": "geometry_msgs/msg/Vector3",
      "hash_string": "RIHS01_cc12fe83e4c02719f1ce8070bfd14aecd40f75a96696a67a2a1f37f7dbb0765d"
    },
    {
      "type_name": "service_msgs/msg/ServiceEventInfo",
      "hash_string": "RIHS01_41bcbbe07a75c9b52bc96bfd5c24d7f0fc0a08c0cb7921b3373c5732345a6f45"
    },
    {
      "type_name": "std_msgs/msg/Header",
      "hash_string": "RIHS01_f49fb3ae2cf070f793645ff749683ac6b06203e41c891e17701b1cb597ce6a01"
    },
    {
      "type_name": "unique_identifier_msgs/msg/UUID",
      "hash_string": "RIHS01_1b8e8aca958cbea28fe6ef60bf6c19b683c97a9ef60bb34752067d0f2f7ab437"
    }
  ]
}